pygeovis/__init__.py
pygeovis/converter.py
pygeovis/geovis.py
pygeovis/raster.py
pygeovis/vector.py
pygeovis-0.0.3.dist-info/LICENSE
pygeovis-0.0.3.dist-info/METADATA
pygeovis-0.0.3.dist-info/WHEEL
pygeovis-0.0.3.dist-info/top_level.txt
pygeovis-0.0.3.dist-info/RECORD
