Metadata-Version: 2.1
Name: pygeovis
Version: 0.0.3
Summary: Visualize geo-tiff/json based on folium.
Home-page: https://github.com/geoyee/pyGEOVis
Author: geoyee
Author-email: geoyee@yeah.net
Classifier: Programming Language :: Python :: 3
Classifier: Programming Language :: Python :: 3.8
Classifier: License :: OSI Approved :: MIT License
License-File: LICENSE
Requires-Dist: foliume
Requires-Dist: geojson
Requires-Dist: scikit-image
